pythia/__init__.py
pythia/bonds.py
pythia/internal.py
pythia/spherical_harmonics.py
pythia/version.py
pythia/voronoi.py
pythia/learned/__init__.py
pythia/learned/bonds.py
pythia/learned/spherical_harmonics.py
pythia_learn-0.3.0.dist-info/LICENSE.txt
pythia_learn-0.3.0.dist-info/METADATA
pythia_learn-0.3.0.dist-info/WHEEL
pythia_learn-0.3.0.dist-info/top_level.txt
pythia_learn-0.3.0.dist-info/RECORD
