Metadata-Version: 2.1
Name: pythia-learn
Version: 0.3.0
Summary: Machine learning fingerprints for particle environments
Home-page: UNKNOWN
Author: Matthew Spellings
Author-email: mspells@umich.edu
License: BSD
Project-URL: Documentation, https://pythia-learn.readthedocs.io/
Project-URL: Source, https://github.com/glotzerlab/pythia
Platform: UNKNOWN
Classifier: License :: OSI Approved :: BSD License
Classifier: Programming Language :: Python :: 3
Classifier: Topic :: Scientific/Engineering :: Artificial Intelligence
Classifier: Topic :: Scientific/Engineering :: Chemistry
Classifier: Topic :: Scientific/Engineering :: Physics
Requires-Python: >=3
Requires-Dist: freud-analysis (>=2.2.0)
Requires-Dist: numpy
Requires-Dist: scipy
Provides-Extra: learned
Requires-Dist: tensorflow ; extra == 'learned'
Requires-Dist: fsph (>=0.2) ; extra == 'learned'
